{
  "db_name": "PostgreSQL",
  "query": "UPDATE entities SET label = $1, description = $2, author = $3, source = $4 WHERE  id = $5 AND owner_id = $6 RETURNING *",
  "describe": {
    "columns": [
      {
        "ordinal": 0,
        "name": "id",
        "type_info": "Int8"
      },
      {
        "ordinal": 1,
        "name": "uuid",
        "type_info": "Uuid"
      },
      {
        "ordinal": 2,
        "name": "label",
        "type_info": "Text"
      },
      {
        "ordinal": 3,
        "name": "description",
        "type_info": "Text"
      },
      {
        "ordinal": 4,
        "name": "author",
        "type_info": "Text"
      },
      {
        "ordinal": 5,
        "name": "source",
        "type_info": "Text"
      },
      {
        "ordinal": 6,
        "name": "visibility",
        "type_info": "Varchar"
      },
      {
        "ordinal": 7,
        "name": "org_id",
        "type_info": "Int8"
      },
      {
        "ordinal": 8,
        "name": "ctime",
        "type_info": "Timestamptz"
      },
      {
        "ordinal": 9,
        "name": "mtime",
        "type_info": "Timestamptz"
      },
      {
        "ordinal": 10,
        "name": "owner_id",
        "type_info": "Int8"
      }
    ],
    "parameters": {
      "Left": [
        "Text",
        "Text",
        "Text",
        "Text",
        "Int8",
        "Int8"
      ]
    },
    "nullable": [
      false,
      true,
      false,
      false,
      false,
      false,
      false,
      false,
      true,
      true,
      false
    ]
  },
  "hash": "ec48655dae13ef93b28867369db3629d50210462b9e59412c7d97271cf57df33"
}
